CHANGES.txt
CONTRIBUTORS.txt
LICENSE
MANIFEST.in
README.rst
requirements.txt
setup.cfg
setup.py
cs/__init__.py
cs.at.gipuzkoairekia.egg-info/PKG-INFO
cs.at.gipuzkoairekia.egg-info/SOURCES.txt
cs.at.gipuzkoairekia.egg-info/dependency_links.txt
cs.at.gipuzkoairekia.egg-info/entry_points.txt
cs.at.gipuzkoairekia.egg-info/namespace_packages.txt
cs.at.gipuzkoairekia.egg-info/not-zip-safe
cs.at.gipuzkoairekia.egg-info/paster_plugins.txt
cs.at.gipuzkoairekia.egg-info/requires.txt
cs.at.gipuzkoairekia.egg-info/top_level.txt
cs/at/__init__.py
cs/at/gipuzkoairekia/__init__.py
cs/at/gipuzkoairekia/config.py
cs/at/gipuzkoairekia/configure.zcml
cs/at/gipuzkoairekia/permissions.zcml
cs/at/gipuzkoairekia/rebuild_i18n.sh
cs/at/gipuzkoairekia/testing.py
cs/at/gipuzkoairekia/browser/__init__.py
cs/at/gipuzkoairekia/browser/configure.zcml
cs/at/gipuzkoairekia/browser/opendatafolder.pt
cs/at/gipuzkoairekia/browser/opendatafolder.py
cs/at/gipuzkoairekia/browser/transparency.pt
cs/at/gipuzkoairekia/browser/transparency.py
cs/at/gipuzkoairekia/browser/transparencysection.pt
cs/at/gipuzkoairekia/browser/transparencysection.py
cs/at/gipuzkoairekia/browser/transparencysectionlist.pt
cs/at/gipuzkoairekia/browser/transparencysectionlist.py
cs/at/gipuzkoairekia/browser/resources/moment-with-locales.min.js
cs/at/gipuzkoairekia/content/__init__.py
cs/at/gipuzkoairekia/content/configure.zcml
cs/at/gipuzkoairekia/content/opendatafolder.py
cs/at/gipuzkoairekia/content/transparencysection.py
cs/at/gipuzkoairekia/extender/__init__.py
cs/at/gipuzkoairekia/extender/configure.zcml
cs/at/gipuzkoairekia/extender/gipuzkoairekiafolder.py
cs/at/gipuzkoairekia/interfaces/__init__.py
cs/at/gipuzkoairekia/interfaces/browserlayer.py
cs/at/gipuzkoairekia/interfaces/gipuzkoairekia.py
cs/at/gipuzkoairekia/interfaces/opendatafolder.py
cs/at/gipuzkoairekia/interfaces/transparencysection.py
cs/at/gipuzkoairekia/locales/es/LC_MESSAGES/cs.at.gipuzkoairekia.po
cs/at/gipuzkoairekia/locales/es/LC_MESSAGES/plone.po
cs/at/gipuzkoairekia/locales/eu/LC_MESSAGES/cs.at.gipuzkoairekia.po
cs/at/gipuzkoairekia/locales/eu/LC_MESSAGES/plone.po
cs/at/gipuzkoairekia/profiles/default/browserlayer.xml
cs/at/gipuzkoairekia/profiles/default/factorytool.xml
cs/at/gipuzkoairekia/profiles/default/metadata.xml
cs/at/gipuzkoairekia/profiles/default/rolemap.xml
cs/at/gipuzkoairekia/profiles/default/types.xml
