Metadata-Version: 2.1
Name: cs.at.gipuzkoairekia
Version: 1.0.1
Summary: An add-on for Plone to expose the contents of Gipuzkoa Irekia, an open government platform
Home-page: https://github.com/codesyntax/cs.at.gipuzkoairekia
Author: Mikel Larreategi
Author-email: mlarreategi@codesyntax.com
License: GPL
Platform: UNKNOWN
Classifier: Environment :: Web Environment
Classifier: Framework :: Plone
Classifier: Framework :: Plone :: 4.3
Classifier: Programming Language :: Python
Classifier: Programming Language :: Python :: 2.7
Classifier: Operating System :: OS Independent
Classifier: License :: OSI Approved :: GNU General Public License v2 (GPLv2)
Provides-Extra: test
